{
  "BT-A": {
    "id": "BT-A",
    "name": "Ideal backtest",
    "bets": 451,
    "wins": 230,
    "losses": 221,
    "win_rate_pct": 51.0,
    "total_pnl_usd": 21.26,
    "total_fees_usd": 0.0,
    "start_balance_usd": 241.83,
    "end_balance_usd": 263.09,
    "net_return_pct": 8.79,
    "max_drawdown_usd": 72.99,
    "max_drawdown_pct": 23.25,
    "long_bets": 271,
    "long_win_rate_pct": 49.45,
    "short_bets": 180,
    "short_win_rate_pct": 53.33
  },
  "BT-B": {
    "id": "BT-B",
    "name": "Doc backtest",
    "bets": 451,
    "wins": 230,
    "losses": 221,
    "win_rate_pct": 51.0,
    "total_pnl_usd": -8.9,
    "total_fees_usd": 30.9,
    "start_balance_usd": 241.83,
    "end_balance_usd": 232.92,
    "net_return_pct": -3.68,
    "max_drawdown_usd": 79.82,
    "max_drawdown_pct": 27.12,
    "long_bets": 271,
    "long_win_rate_pct": 49.45,
    "short_bets": 180,
    "short_win_rate_pct": 53.33
  },
  "BT-C": {
    "id": "BT-C",
    "name": "Prod-faithful",
    "bets": 288,
    "wins": 134,
    "losses": 154,
    "win_rate_pct": 46.53,
    "total_pnl_usd": -32.45,
    "total_fees_usd": 0.0,
    "start_balance_usd": 241.83,
    "end_balance_usd": 209.37,
    "net_return_pct": -13.42,
    "max_drawdown_usd": 112.15,
    "max_drawdown_pct": 35.03,
    "long_bets": 165,
    "long_win_rate_pct": 46.67,
    "short_bets": 123,
    "short_win_rate_pct": 46.34
  },
  "BT-D": {
    "id": "BT-D",
    "name": "Prod-faithful compound",
    "bets": 311,
    "wins": 142,
    "losses": 169,
    "win_rate_pct": 45.66,
    "total_pnl_usd": -86.09,
    "total_fees_usd": 0.0,
    "start_balance_usd": 241.83,
    "end_balance_usd": 155.74,
    "net_return_pct": -35.6,
    "max_drawdown_usd": 112.54,
    "max_drawdown_pct": 41.95,
    "long_bets": 186,
    "long_win_rate_pct": 45.16,
    "short_bets": 125,
    "short_win_rate_pct": 46.4
  },
  "BT-E": {
    "id": "BT-E",
    "name": "Signal-only",
    "bets": 451,
    "wins": 230,
    "losses": 221,
    "win_rate_pct": 51.0,
    "total_pnl_usd": 0.0,
    "total_fees_usd": 0.0,
    "start_balance_usd": 241.83,
    "end_balance_usd": 0.0,
    "net_return_pct": -100.0,
    "max_drawdown_usd": 0.0,
    "max_drawdown_pct": 0.0,
    "long_bets": 0,
    "long_win_rate_pct": 0,
    "short_bets": 0,
    "short_win_rate_pct": 0
  },
  "PROD": {
    "id": "PROD",
    "name": "Live production (Binance cov.)",
    "bets": 288,
    "wins": 134,
    "losses": 154,
    "win_rate_pct": 46.53,
    "total_pnl_usd": -31.37,
    "total_pnl_all_usd": -54.77,
    "total_fees_usd": 0,
    "start_balance_usd": 241.83,
    "end_balance_usd": 210.45,
    "net_return_pct": -12.97,
    "max_drawdown_usd": "n/a",
    "long_bets": 165,
    "short_bets": 123
  }
}